incremental/__init__.py
incremental/_hatch.py
incremental/_version.py
incremental/py.typed
incremental/update.py
incremental/tests/__init__.py
incremental/tests/test_pyproject.py
incremental/tests/test_update.py
incremental/tests/test_version.py
incremental-24.7.1.dist-info/LICENSE
incremental-24.7.1.dist-info/METADATA
incremental-24.7.1.dist-info/WHEEL
incremental-24.7.1.dist-info/entry_points.txt
incremental-24.7.1.dist-info/top_level.txt
incremental-24.7.1.dist-info/RECORD
