Metadata-Version: 2.1
Name: incremental
Version: 24.7.1
Summary: A small library that versions your Python projects.
Maintainer-email: Amber Brown <hawkowl@twistedmatrix.com>
Project-URL: Homepage, https://github.com/twisted/incremental
Project-URL: Documentation, https://twisted.org/incremental/docs/
Project-URL: Issues, https://github.com/twisted/incremental/issues
Project-URL: Changelog, https://github.com/twisted/incremental/blob/trunk/NEWS.rst
Classifier: Intended Audience :: Developers
Classifier: License :: OSI Approved :: MIT License
Classifier: Framework :: Hatch
Classifier: Framework :: Setuptools Plugin
Classifier: Programming Language :: Python :: 3
Classifier: Programming Language :: Python :: 3.8
Classifier: Programming Language :: Python :: 3.9
Classifier: Programming Language :: Python :: 3.10
Classifier: Programming Language :: Python :: 3.11
Classifier: Programming Language :: Python :: 3.12
Requires-Python: >=3.8
License-File: LICENSE
Requires-Dist: setuptools>=61.0
Requires-Dist: tomli; python_version < "3.11"
Provides-Extra: scripts
Requires-Dist: click>=6.0; extra == "scripts"
